README.md
setup.cfg
setup.py
bookstack_dl/__init__.py
bookstack_dl.egg-info/PKG-INFO
bookstack_dl.egg-info/SOURCES.txt
bookstack_dl.egg-info/dependency_links.txt
bookstack_dl.egg-info/requires.txt
bookstack_dl.egg-info/top_level.txt