Metadata-Version: 2.1
Name: bookstack-dl
Version: 0.1.1
Summary: Automatically export all pages in Bookstack.
Home-page: https://gitlab.com/rveach/bookstack-dl
Author: Ryan Veach
Author-email: rveach@gmail.com
License: MIT
Keywords: Bookstack,BookstackApp
Platform: UNKNOWN
Classifier: Development Status :: 4 - Beta
Classifier: Intended Audience :: Developers
Classifier: Intended Audience :: Information Technology
Classifier: Intended Audience :: System Administrators
Classifier: License :: OSI Approved :: MIT License
Classifier: Topic :: Software Development :: Libraries :: Python Modules
Classifier: Topic :: Internet
Classifier: Programming Language :: Python :: 3
Classifier: Programming Language :: Python :: 3.6
Classifier: Programming Language :: Python :: 3.7
Classifier: Programming Language :: Python :: 3.8
Requires-Python: >=3.6
